cozifytemp/__init__.py
cozifytemp/cache.py
cozifytemp/config.py
cozifytemp/sample_loop.py
cozifytemp/single_sample.py
cozifytemp/storage.py
cozifytemp/util.py
cozifytemp-0.1.4.dist-info/LICENSE
cozifytemp-0.1.4.dist-info/METADATA
cozifytemp-0.1.4.dist-info/WHEEL
cozifytemp-0.1.4.dist-info/entry_points.txt
cozifytemp-0.1.4.dist-info/RECORD
