Metadata-Version: 2.1
Name: cozifytemp
Version: 0.1.4
Summary: Sample Cozify sensor to influxdb logger
License: MIT
Author: Artanicus
Author-email: artanicus@nocturnal.fi
Requires-Python: >=3.8,<4.0
Classifier: License :: OSI Approved :: MIT License
Classifier: Programming Language :: Python :: 3
Classifier: Programming Language :: Python :: 3.8
Classifier: Programming Language :: Python :: 3.9
Classifier: Programming Language :: Python :: 3.10
Classifier: Programming Language :: Python :: 3.11
Requires-Dist: absl-py (>=1.0.0,<2.0.0)
Requires-Dist: cozify (==0.2.33)
Requires-Dist: influxdb-client (>=1.19.0,<2.0.0)
Requires-Dist: pytz (>=2021.1,<2022.0)
Requires-Dist: requests (>=2.26.0,<3.0.0)
